teamflow_console/__init__.py
teamflow_console/cli/__init__.py
teamflow_console/cli/menus.py
teamflow_console/cli/prompts.py
teamflow_console/lib/__init__.py
teamflow_console/lib/formatting.py
teamflow_console/lib/storage.py
teamflow_console/lib/validation.py
teamflow_console/models/__init__.py
teamflow_console/models/task.py
teamflow_console/models/team.py
teamflow_console/models/user.py
teamflow_console/services/__init__.py
teamflow_console/services/menu_service.py
teamflow_console/services/task_service.py
teamflow_console/services/team_service.py
teamflow_console/services/user_service.py
teamflow_console-0.2.4.dist-info/METADATA
teamflow_console-0.2.4.dist-info/WHEEL
teamflow_console-0.2.4.dist-info/entry_points.txt
teamflow_console-0.2.4.dist-info/licenses/LICENSE
teamflow_console-0.2.4.dist-info/RECORD
