Metadata-Version: 2.4
Name: teamflow-console
Version: 0.2.4
Summary: TeamFlow Console App - Phase 1: In-Memory Task Distribution
Project-URL: Homepage, https://github.com/MrOwaisAbdullah/Teamflow
Project-URL: Documentation, https://github.com/MrOwaisAbdullah/Teamflow#readme
Project-URL: Repository, https://github.com/MrOwaisAbdullah/Teamflow
Project-URL: Bug Tracker, https://github.com/MrOwaisAbdullah/Teamflow/issues
Author-email: Owais Abdullah <contact@owaisabdullah.dev>
Maintainer-email: Owais Abdullah <contact@owaisabdullah.dev>
License: MIT
License-File: LICENSE
Keywords: cli,productivity,task-management,team,terminal
Classifier: Development Status :: 3 - Alpha
Classifier: Environment :: Console
Classifier: Intended Audience :: Developers
Classifier: License :: OSI Approved :: MIT License
Classifier: Operating System :: OS Independent
Classifier: Programming Language :: Python :: 3
Classifier: Programming Language :: Python :: 3.13
Classifier: Topic :: Office/Business :: Scheduling
Classifier: Topic :: Utilities
Requires-Python: >=3.13
Requires-Dist: pydantic>=2.5.0
Requires-Dist: rich>=13.7.0
Requires-Dist: typer>=0.12.0
Provides-Extra: dev
Requires-Dist: black>=23.12.0; extra == 'dev'
Requires-Dist: build>=0.10.0; extra == 'dev'
Requires-Dist: isort>=5.13.0; extra == 'dev'
Requires-Dist: mypy>=1.7.0; extra == 'dev'
Requires-Dist: pylint>=3.0.0; extra == 'dev'
Requires-Dist: pytest-cov>=4.1.0; extra == 'dev'
Requires-Dist: pytest-mock>=3.12.0; extra == 'dev'
Requires-Dist: pytest>=7.4.0; extra == 'dev'
Requires-Dist: twine>=4.0.0; extra == 'dev'
